Metadata-Version: 2.1
Name: odoo12-addon-purchase-order-line-packaging-qty
Version: 12.0.1.2.0
Summary: Define quantities according to product packaging on purchase order lines
Home-page: https://github.com/OCA/purchase-workflow
Author: ForgeFlow, Odoo Community Association (OCA)
Author-email: support@odoo-community.org
License: AGPL-3
Platform: UNKNOWN
Classifier: Programming Language :: Python
Classifier: Framework :: Odoo
Classifier: Framework :: Odoo :: 12.0
Classifier: License :: OSI Approved :: GNU Affero General Public License v3
Classifier: Development Status :: 3 - Alpha
Requires-Python: >=3.5
Requires-Dist: odoo12-addon-stock-move-packaging-qty
Requires-Dist: odoo (<12.1dev,>=12.0a)
